conftest.py
haploblock_shuffler/__init__.py
haploblock_shuffler/__main__.py
haploblock_shuffler/cli.py
haploblock_shuffler/utils.py
haploblock_shuffler-0.0.6.dist-info/METADATA
haploblock_shuffler-0.0.6.dist-info/WHEEL
haploblock_shuffler-0.0.6.dist-info/entry_points.txt
haploblock_shuffler-0.0.6.dist-info/top_level.txt
haploblock_shuffler-0.0.6.dist-info/RECORD
