Metadata-Version: 2.1
Name: haploblock-shuffler
Version: 0.0.6
Summary: Create all possible combinations of phased and unphased blocks in a vcf
Home-page: https://github.com/redmar-van-den-berg/haploblock-shuffler
Author: Redmar van den Berg
Author-email: RedmarvandenBerg@lumc.nl
License: MIT
Project-URL: Changelog, https://github.com/redmar-van-den-berg/haploblock-shuffler/blob/master/CHANGELOG.md
Project-URL: Issue Tracker, https://github.com/redmar-van-den-berg/haploblock-shuffler/issues
Platform: UNKNOWN
Classifier: Development Status :: 3 - Alpha
Classifier: Intended Audience :: Developers
Classifier: License :: OSI Approved :: BSD License
Classifier: Operating System :: Unix
Classifier: Programming Language :: Python
Classifier: Programming Language :: Python :: 3
Classifier: Programming Language :: Python :: 3.7
Classifier: Programming Language :: Python :: 3.8
Classifier: Programming Language :: Python :: 3.9
Classifier: Programming Language :: Python :: 3.10
Classifier: Topic :: Utilities
Requires-Python: >=3.7.*
Requires-Dist: pyvcf3
